[
    {
        "task": "22",
        "created_time": 1490336013,
        "finish": false,
        "project_id": 3,
        "id": 1
    },
    {
        "task": "ee",
        "created_time": 1490336072,
        "finish": false,
        "project_id": 3,
        "id": 2
    },
    {
        "task": "eefa",
        "created_time": 1490336090,
        "finish": false,
        "project_id": 4,
        "id": 3
    },
    {
        "task": "fdsafda",
        "created_time": 1490336093,
        "finish": false,
        "project_id": 4,
        "id": 4
    },
    {
        "task": "1111",
        "created_time": 1490336095,
        "finish": false,
        "project_id": 4,
        "id": 5
    },
    {
        "task": "222222",
        "created_time": 1490336097,
        "finish": false,
        "project_id": 4,
        "id": 6
    },
    {
        "task": "ehdaf",
        "created_time": 1490336120,
        "finish": false,
        "project_id": 2,
        "id": 7
    },
    {
        "task": "xx吃过",
        "created_time": 1490336125,
        "finish": false,
        "project_id": 2,
        "id": 8
    },
    {
        "task": "哼哼",
        "created_time": 1490336128,
        "finish": false,
        "project_id": 2,
        "id": 9
    },
    {
        "task": "刚当当",
        "created_time": 1490336131,
        "finish": false,
        "project_id": 2,
        "id": 10
    },
    {
        "task": "66",
        "created_time": 1490337014,
        "finish": false,
        "project_id": null,
        "id": 16
    }
]